arp_sdk/__init__.py
arp_sdk/errors.py
arp_sdk/py.typed
arp_sdk/clients/__init__.py
arp_sdk/clients/daemon.py
arp_sdk/clients/runtime.py
arp_sdk/clients/tool_registry.py
arp_sdk/daemon/__init__.py
arp_sdk/daemon/client.py
arp_sdk/daemon/errors.py
arp_sdk/daemon/sdk.py
arp_sdk/daemon/types.py
arp_sdk/daemon/api/__init__.py
arp_sdk/daemon/api/health/__init__.py
arp_sdk/daemon/api/health/health.py
arp_sdk/daemon/api/instances/__init__.py
arp_sdk/daemon/api/instances/create_instances.py
arp_sdk/daemon/api/instances/delete_instance.py
arp_sdk/daemon/api/instances/list_instances.py
arp_sdk/daemon/api/instances/register_instance.py
arp_sdk/daemon/api/runs/__init__.py
arp_sdk/daemon/api/runs/get_run_result.py
arp_sdk/daemon/api/runs/get_run_status.py
arp_sdk/daemon/api/runs/get_run_trace.py
arp_sdk/daemon/api/runs/list_runs.py
arp_sdk/daemon/api/runs/submit_run.py
arp_sdk/daemon/api/runtime_profiles/__init__.py
arp_sdk/daemon/api/runtime_profiles/delete_runtime_profile.py
arp_sdk/daemon/api/runtime_profiles/list_runtime_profiles.py
arp_sdk/daemon/api/runtime_profiles/upsert_runtime_profile.py
arp_sdk/daemon/api/version/__init__.py
arp_sdk/daemon/api/version/version.py
arp_sdk/daemon/models/__init__.py
arp_sdk/daemon/models/error_envelope.py
arp_sdk/daemon/models/error_envelope_error.py
arp_sdk/daemon/models/error_envelope_error_details.py
arp_sdk/daemon/models/error_envelope_error_error_cause.py
arp_sdk/daemon/models/error_envelope_error_error_cause_details.py
arp_sdk/daemon/models/error_envelope_error_error_cause_extensions.py
arp_sdk/daemon/models/error_envelope_error_extensions.py
arp_sdk/daemon/models/error_envelope_extensions.py
arp_sdk/daemon/models/health.py
arp_sdk/daemon/models/health_checks_item.py
arp_sdk/daemon/models/health_checks_item_details.py
arp_sdk/daemon/models/health_checks_item_status.py
arp_sdk/daemon/models/health_extensions.py
arp_sdk/daemon/models/health_status.py
arp_sdk/daemon/models/instance_create_request.py
arp_standard_py-0.1.0.dist-info/licenses/LICENSE
arp_standard_py-0.1.0.dist-info/METADATA
arp_standard_py-0.1.0.dist-info/WHEEL
arp_standard_py-0.1.0.dist-info/top_level.txt
arp_standard_py-0.1.0.dist-info/RECORD
