Metadata-Version: 2.4
Name: arp-standard-py
Version: 0.1.0
Summary: Python SDK for the ARP Standard (v1).
Author: Agent Runtime Protocol
License: MIT License
Project-URL: Repository, https://github.com/AgentRuntimeProtocol/ARP_Standard
Project-URL: Issues, https://github.com/AgentRuntimeProtocol/ARP_Standard/issues
Requires-Python: >=3.10
License-File: LICENSE
Requires-Dist: attrs>=22.2.0
Requires-Dist: httpx>=0.23.0
Requires-Dist: python-dateutil>=2.8.1
Provides-Extra: dev
Requires-Dist: pytest>=7; extra == "dev"
Requires-Dist: pyright>=1.1.0; extra == "dev"
Dynamic: license-file
